pipops/__init__.py
pipops/canary/__init__.py
pipops/canary/canary_analysis.py
pipops-0.1.2.data/scripts/__init__.py
pipops-0.1.2.dist-info/LICENSE.txt
pipops-0.1.2.dist-info/METADATA
pipops-0.1.2.dist-info/WHEEL
pipops-0.1.2.dist-info/top_level.txt
pipops-0.1.2.dist-info/RECORD
