Metadata-Version: 2.1
Name: pipops
Version: 0.1.2
Summary: PipOps is an AiOps inspired project created and self managed by Vishal Raj (DevOps Specialist)
Home-page: https://github.com/iiamvishalraj
Author: Vishal Raj
Author-email: iiamvishalraj@gmail.com
License: Apache 2.0
Platform: UNKNOWN
Classifier: Development Status :: 3 - Alpha
Classifier: Intended Audience :: Developers
Classifier: Topic :: Software Development :: Build Tools
Classifier: Programming Language :: Python :: 3
Classifier: Programming Language :: Python :: 3.8
Requires-Dist: numpy (>=1.19.2)
Requires-Dist: scipy (>=1.5.2)
